LICENCE
README.md
setup.py
pymathutilslib/__init__.py
pymathutilslib/utilidade1.py
pymathutilslib/utilidade2.py
pymathutilslib_v001.egg-info/PKG-INFO
pymathutilslib_v001.egg-info/SOURCES.txt
pymathutilslib_v001.egg-info/dependency_links.txt
pymathutilslib_v001.egg-info/top_level.txt